texas/__init__.py
texas/card.py
texas/data/5.pickle
texas/data/6.pickle
texas/data/7.pickle
texas/data/rank.pickle
texas/hand.py
texas/helper.py
texas/holdem/action.py
texas/holdem/dealer.py
texas/holdem/holdem.py
texas/holdem/player.py
texas/holdem/position.py
texas/holdem/round.py
texas/holdem/typed_dict.py
texas/sample/simple_call_bot_heads_up.py
texas/sub/probability.py
texas-0.0.2.dist-info/WHEEL
texas-0.0.2.dist-info/METADATA
texas-0.0.2.dist-info/RECORD
