Metadata-Version: 2.1
Name: texas
Version: 0.0.2
Summary: テキサスホールデムのpython実装です
Home-page: https://github.com/agarichan/texas
License: MIT
Author: agarichan
Requires-Python: >=3.8,<4.0
Classifier: License :: OSI Approved :: MIT License
Classifier: Programming Language :: Python :: 3
Classifier: Programming Language :: Python :: 3.10
Classifier: Programming Language :: Python :: 3.8
Classifier: Programming Language :: Python :: 3.9
Provides-Extra: sample
Requires-Dist: rich (>=11.1.0,<12.0.0); extra == "sample"
Project-URL: Repository, https://github.com/agarichan/texas
